rbloom_gcs-1.5.6.dist-info/METADATA
rbloom_gcs-1.5.6.dist-info/WHEEL
rbloom_gcs-1.5.6.dist-info/licenses/LICENSE
rbloom.libs/libcom_err-2abe824b.so.2
rbloom.libs/libcrypto-d3570994.so.10
rbloom.libs/libgssapi_krb5-497db0c6.so.2
rbloom.libs/libk5crypto-b1f99d5c.so.3
rbloom.libs/libkeyutils-dfe70bd6.so.1
rbloom.libs/libkrb5-fcafa220.so.3
rbloom.libs/libkrb5support-d0bcff84.so.0
rbloom.libs/libpcre-9513aab5.so.1
rbloom.libs/libselinux-0922c95c.so.1
rbloom.libs/libssl-cd1d6220.so.10
rbloom/__init__.py
rbloom/__init__.pyi
rbloom/py.typed
rbloom/rbloom.abi3.so
rbloom_gcs-1.5.6.dist-info/RECORD
